kozmoml_lightgbm/__init__.py
kozmoml_lightgbm/lightgbm.py
kozmoml_lightgbm/version.py
kozmoml_lightgbm-0.1.0.dev1.dist-info/LICENSE
kozmoml_lightgbm-0.1.0.dev1.dist-info/METADATA
kozmoml_lightgbm-0.1.0.dev1.dist-info/WHEEL
kozmoml_lightgbm-0.1.0.dev1.dist-info/RECORD
